quinkgl/__init__.py
quinkgl/config.py
quinkgl/aggregation/__init__.py
quinkgl/aggregation/base.py
quinkgl/aggregation/fedavg.py
quinkgl/core/__init__.py
quinkgl/core/context.py
quinkgl/core/dummy_model.py
quinkgl/core/model_interface.py
quinkgl/core/node.py
quinkgl/data/__init__.py
quinkgl/data/datasets.py
quinkgl/gossip/__init__.py
quinkgl/gossip/orchestrator.py
quinkgl/gossip/protocol.py
quinkgl/models/__init__.py
quinkgl/models/base.py
quinkgl/models/pytorch.py
quinkgl/models/tensorflow.py
quinkgl/network/__init__.py
quinkgl/network/connection_manager.py
quinkgl/network/gossip_community.py
quinkgl/network/gossip_node.py
quinkgl/network/gossip_pb2.py
quinkgl/network/gossip_pb2_grpc.py
quinkgl/network/grpc_node.py
quinkgl/network/ipv8_community.py
quinkgl/network/ipv8_manager.py
quinkgl/network/model_serializer.py
quinkgl/network/tunnel_client.py
quinkgl/network/tunnel_pb2.py
quinkgl/network/tunnel_pb2_grpc.py
quinkgl/storage/__init__.py
quinkgl/storage/model_store.py
quinkgl/topology/__init__.py
quinkgl/topology/base.py
quinkgl/topology/cyclon.py
quinkgl/topology/random.py
quinkgl/topology/sampler.py
quinkgl/utils/serialization.py
quinkgl-0.1.18.dist-info/METADATA
quinkgl-0.1.18.dist-info/WHEEL
quinkgl-0.1.18.dist-info/top_level.txt
quinkgl-0.1.18.dist-info/RECORD
