Metadata-Version: 2.4
Name: quinkgl
Version: 0.1.18
Summary: A decentralized gossip learning framework for P2P edge intelligence
Author-email: Ali Seyhan <aliseyhan@posta.mu.edu.tr>, Baki Turhan <bakiturhan@posta.mu.edu.tr>
Project-URL: Homepage, https://github.com/aliseyhann/QuinkGL-Gossip-Learning-Framework
Project-URL: Bug Tracker, https://github.com/aliseyhann/QuinkGL-Gossip-Learning-Framework/issues
Keywords: gossip-learning,federated-learning,p2p,decentralized-ai,ipv8
Classifier: Programming Language :: Python :: 3
Classifier: License :: OSI Approved :: MIT License
Classifier: Operating System :: OS Independent
Classifier: Topic :: Scientific/Engineering :: Artificial Intelligence
Classifier: Topic :: System :: Distributed Computing
Requires-Python: >=3.9
Requires-Dist: numpy>=1.24.0
Requires-Dist: torch>=2.0.0
Requires-Dist: torchvision>=0.15.0
Requires-Dist: scikit-learn>=1.0.0
Requires-Dist: pandas>=1.5.0
Requires-Dist: pyipv8>=2.10.0
Requires-Dist: grpcio>=1.50.0
Requires-Dist: grpcio-tools>=1.50.0
Requires-Dist: protobuf>=4.20.0
Requires-Dist: msgpack>=1.0.0
Provides-Extra: tensorflow
Requires-Dist: tensorflow>=2.12.0; extra == "tensorflow"
Provides-Extra: dev
Requires-Dist: pytest>=7.0.0; extra == "dev"
Requires-Dist: pytest-asyncio>=0.21.0; extra == "dev"
Requires-Dist: black>=23.0.0; extra == "dev"
Requires-Dist: flake8>=6.0.0; extra == "dev"
Requires-Dist: mypy>=1.0.0; extra == "dev"
Provides-Extra: all
Requires-Dist: quinkgl[tensorflow]; extra == "all"
